[
    {
        "id": 2211,
        "name": "Sony Gamepad",
        "slug": "sony-gamepad",
        "permalink": "https://wclovers.mstore.io/product/sony-gamepad/",
        "date_created": "2018-08-17T17:54:01",
        "date_created_gmt": "2018-08-17T10:54:01",
        "date_modified": "2021-01-12T05:12:32",
        "date_modified_gmt": "2021-01-11T22:12:32",
        "type": "variable",
        "status": "publish",
        "featured": true,
        "catalog_visibility": "visible",
        "description": "<p>Pellentesque habitant morbi tristique senectus et netus et malesuada fames ac turpis egestas. Vestibulum tortor quam, feugiat vitae, ultricies eget, tempor sit amet, ante. Donec eu libero sit amet quam egestas semper. Aenean ultricies mi vitae est. Mauris placerat eleifend leo.</p>\n",
        "short_description": "<p>Pellentesque habitant morbi tristique senectus et netus et malesuada fames ac turpis egestas. Vestibulum tortor quam, feugiat vitae, ultricies eget, tempor sit amet, ante. Donec eu libero sit amet quam egestas semper. Aenean ultricies mi vitae est. Mauris placerat eleifend leo.</p>\n",
        "sku": "",
        "price": "110",
        "regular_price": "",
        "sale_price": "",
        "date_on_sale_from": null,
        "date_on_sale_from_gmt": null,
        "date_on_sale_to": null,
        "date_on_sale_to_gmt": null,
        "price_html": "<span class=\"woocommerce-Price-amount amount\"><span class=\"woocommerce-Price-currencySymbol\">&#36;</span>110.00</span> &ndash; <span class=\"woocommerce-Price-amount amount\"><span class=\"woocommerce-Price-currencySymbol\">&#36;</span>120.00</span>",
        "on_sale": true,
        "purchasable": true,
        "total_sales": 10,
        "virtual": false,
        "downloadable": false,
        "downloads": [],
        "download_limit": -1,
        "download_expiry": -1,
        "external_url": "",
        "button_text": "",
        "tax_status": "taxable",
        "tax_class": "",
        "manage_stock": true,
        "stock_quantity": 9,
        "in_stock": true,
        "backorders": "no",
        "backorders_allowed": false,
        "backordered": false,
        "sold_individually": false,
        "weight": "",
        "dimensions": {
            "length": "",
            "width": "",
            "height": ""
        },
        "shipping_required": true,
        "shipping_taxable": true,
        "shipping_class": "",
        "shipping_class_id": 0,
        "reviews_allowed": true,
        "average_rating": "0.00",
        "rating_count": 0,
        "related_ids": [
            1334,
            1322,
            2189,
            1295,
            722
        ],
        "upsell_ids": [],
        "cross_sell_ids": [],
        "parent_id": 0,
        "purchase_note": "",
        "categories": [
            {
                "id": 37,
                "name": "Gamepad",
                "slug": "gamepad"
            }
        ],
        "tags": [],
        "images": [
            {
                "id": 526,
                "date_created": "2018-04-27T15:30:47",
                "date_created_gmt": "2018-04-27T08:30:47",
                "date_modified": "2020-12-01T07:21:53",
                "date_modified_gmt": "2020-11-30T17:21:53",
                "src": "https://wclovers.mstore.io/wp-content/uploads/2013/06/Gamepad-for-Sony-Playstation-3.jpg",
                "name": "Gamepad-for-Sony-Playstation-3",
                "alt": "",
                "position": 0
            },
            {
                "id": 525,
                "date_created": "2018-04-27T15:30:45",
                "date_created_gmt": "2018-04-27T08:30:45",
                "date_modified": "2020-12-01T07:21:53",
                "date_modified_gmt": "2020-11-30T17:21:53",
                "src": "https://wclovers.mstore.io/wp-content/uploads/2013/06/Gen-Game-Gamepad-for-Sony-Playstation-3.jpg",
                "name": "Gen-Game-Gamepad-for-Sony-Playstation-3",
                "alt": "",
                "position": 1
            },
            {
                "id": 526,
                "date_created": "2018-04-27T15:30:47",
                "date_created_gmt": "2018-04-27T08:30:47",
                "date_modified": "2020-12-01T07:21:53",
                "date_modified_gmt": "2020-11-30T17:21:53",
                "src": "https://wclovers.mstore.io/wp-content/uploads/2013/06/Gamepad-for-Sony-Playstation-3.jpg",
                "name": "Gamepad-for-Sony-Playstation-3",
                "alt": "",
                "position": 2
            }
        ],
        "attributes": [
            {
                "id": 0,
                "name": "Gamepad",
                "position": 2,
                "visible": true,
                "variation": true,
                "options": [
                    "Black",
                    "White"
                ]
            }
        ],
        "default_attributes": [],
        "variations": [
            2212,
            2213
        ],
        "grouped_products": [],
        "menu_order": 0,
        "meta_data": [
            {
                "id": 16646,
                "key": "_marketpress_deal_date",
                "value": "2018-06-23"
            },
            {
                "id": 16647,
                "key": "_marketpress_deal_title",
                "value": "<span class=\"color-primary\">Hurry up!</span> Offers ends in:"
            },
            {
                "id": 16648,
                "key": "_marketo_deal_date",
                "value": "2019-12-30"
            },
            {
                "id": 16649,
                "key": "_marketo_deal_title",
                "value": "<span class=\"color-primary\">Hurry up!</span> Offers ends in:"
            },
            {
                "id": 16650,
                "key": "pageview",
                "value": "5"
            },
            {
                "id": 16721,
                "key": "_wcmp_child_product",
                "value": "1"
            },
            {
                "id": 16726,
                "key": "slide_template",
                "value": "default"
            },
            {
                "id": 16727,
                "key": "_wcmp_cancallation_policy",
                "value": ""
            },
            {
                "id": 16728,
                "key": "_wcmp_refund_policy",
                "value": ""
            },
            {
                "id": 16729,
                "key": "_wcmp_shipping_policy",
                "value": ""
            },
            {
                "id": 16880,
                "key": "_wcfm_product_views",
                "value": "494"
            },
            {
                "id": 27924,
                "key": "_wcfm_product_approved_notified",
                "value": "yes"
            },
            {
                "id": 27925,
                "key": "_wcfmmp_commission",
                "value": {
                    "commission_mode": "global",
                    "commission_percent": "90",
                    "commission_fixed": "",
                    "tax_name": "",
                    "tax_percent": ""
                }
            },
            {
                "id": 29412,
                "key": "_is_multi_parent",
                "value": "2211"
            }
        ],
        "store": {
            "vendor_id": "116",
            "vendor_display_name": null,
            "vendor_shop_name": "Philip Test vendor",
            "formatted_display_name": "Philip Test vendor - Philip Test vendor (#116 - philiptestvv111@gmail.com)",
            "store_hide_email": "no",
            "store_hide_phone": "no",
            "store_hide_address": "no",
            "store_hide_description": "no",
            "store_hide_policy": "no",
            "store_products_per_page": 10,
            "vendor_email": "philiptestvv111@gmail.com",
            "disable_vendor": false,
            "is_store_offline": "",
            "vendor_shop_logo": "http://wclovers.mstore.io/wp-content/plugins/wc-frontend-manager/assets/images/wcfmmp-blue.png",
            "vendor_banner_type": "image",
            "vendor_banner": "http://wclovers.mstore.io/wp-content/plugins/wc-multivendor-marketplace/assets/images/default_banner.jpg",
            "mobile_banner": "http://wclovers.mstore.io/wp-content/plugins/wc-multivendor-marketplace/assets/images/default_banner.jpg",
            "vendor_list_banner_type": "image",
            "vendor_list_banner": "http://wclovers.mstore.io/wp-content/plugins/wc-multivendor-marketplace/assets/images/default_banner.jpg",
            "store_rating": "",
            "email_verified": "",
            "vendor_additional_info": [],
            "vendor_description": "<p><br data-mce-bogus=\"1\"></p>\n",
            "vendor_policies": {
                "shipping_policy_heading": "Shipping Policy",
                "shipping_policy": "<p><br></p>",
                "refund_policy_heading": "Refund Policy",
                "refund_policy": "<p><br></p>",
                "cancellation_policy_heading": "Cancellation / Return / Exchange Policy",
                "cancellation_policy": "<p><br></p>"
            },
            "store_tab_headings": {
                "products": "Products",
                "about": "About",
                "policies": "Policies",
                "reviews": "Reviews (<span class=\"wcfm_reviews_count\">0</span>)",
                "followers": "Followers (<span class=\"wcfm_followers_count\">0</span>)"
            },
            "settings": {
                "store_name": "Philip Test vendor",
                "store_slug": "philip-test-vendor",
                "store_email": "philiptestvv111@gmail.com",
                "phone": "",
                "vendor_id": "116",
                "gravatar": "",
                "banner_type": "single_img",
                "banner": "",
                "banner_video": "",
                "banner_slider": [
                    {
                        "image": "",
                        "link": ""
                    }
                ],
                "mobile_banner": "",
                "list_banner_type": "single_img",
                "list_banner": "",
                "list_banner_video": "",
                "shop_description": "<p><br data-mce-bogus=\"1\"></p>",
                "address": {
                    "street_1": "",
                    "street_2": "",
                    "city": "",
                    "zip": "",
                    "country": "",
                    "state": ""
                },
                "geolocation": {
                    "store_location": "Hồ Chí Minh, Plei Nhao, Pleiku, Gia Lai Province, Vietnam",
                    "store_lat": "13.9176756",
                    "store_lng": "108.0050126"
                },
                "store_name_position": "on_header",
                "store_ppp": "10",
                "store_hide_email": "no",
                "store_hide_phone": "no",
                "store_hide_address": "no",
                "store_hide_map": "no",
                "store_hide_description": "no",
                "store_hide_policy": "no",
                "store_location": "Hồ Chí Minh, Plei Nhao, Pleiku, Gia Lai Province, Vietnam",
                "store_lat": "13.9176756",
                "store_lng": "108.0050126"
            }
        },
        "is_purchased": false,
        "attributesData": [
            {
                "id": 0,
                "name": "Gamepad",
                "options": [],
                "position": 2,
                "visible": true,
                "variation": true,
                "is_visible": 1,
                "is_variation": 1,
                "is_taxonomy": 0,
                "value": "",
                "label": "Gamepad"
            }
        ],
        "product_units": {
            "weight_unit": "oz",
            "dimension_unit": "in"
        },
        "wcfm_product_policy_data": {
            "visible": true,
            "shipping_policy": "<p><br></p>",
            "shipping_policy_heading": "Shipping Policy",
            "refund_policy": "<p><br></p>",
            "refund_policy_heading": "Refund Policy",
            "cancellation_policy": "<p><br></p>",
            "cancellation_policy_heading": "Cancellation / Return / Exchange Policy",
            "tab_title": "Store Policies"
        },
        "showAdditionalInfoTab": true,
        "_links": {
            "self": [
                {
                    "href": "https://wclovers.mstore.io/wp-json/wc/v2/products/2211"
                }
            ],
            "collection": [
                {
                    "href": "https://wclovers.mstore.io/wp-json/wc/v2/products"
                }
            ]
        }
    },
    {
        "id": 2207,
        "name": "Headset for Phones",
        "slug": "",
        "permalink": "https://wclovers.mstore.io/?post_type=product&p=2207",
        "date_created": "2018-08-17T17:52:32",
        "date_created_gmt": "2018-08-17T10:52:32",
        "date_modified": "2021-01-08T17:00:51",
        "date_modified_gmt": "2021-01-08T10:00:51",
        "type": "simple",
        "status": "draft",
        "featured": false,
        "catalog_visibility": "visible",
        "description": "<p>Donec pede justo, fringilla vel, aliquet nec, vulputate eget, arcu. In enim justo, rhoncus ut, imperdiet a, venenatis vitae, justo.</p>\n",
        "short_description": "<p>utate eget, arcu. In enim justo, rhoncus ut, imperdiet a, venenatis vitae, justo.</p>\n",
        "sku": "",
        "price": "35",
        "regular_price": "39",
        "sale_price": "35",
        "date_on_sale_from": null,
        "date_on_sale_from_gmt": null,
        "date_on_sale_to": null,
        "date_on_sale_to_gmt": null,
        "price_html": "<del><span class=\"woocommerce-Price-amount amount\"><span class=\"woocommerce-Price-currencySymbol\">&#36;</span>39.00</span></del> <ins><span class=\"woocommerce-Price-amount amount\"><span class=\"woocommerce-Price-currencySymbol\">&#36;</span>35.00</span></ins>",
        "on_sale": true,
        "purchasable": true,
        "total_sales": 1,
        "virtual": false,
        "downloadable": false,
        "downloads": [],
        "download_limit": -1,
        "download_expiry": -1,
        "external_url": "",
        "button_text": "",
        "tax_status": "taxable",
        "tax_class": "",
        "manage_stock": true,
        "stock_quantity": 123,
        "in_stock": true,
        "backorders": "no",
        "backorders_allowed": false,
        "backordered": false,
        "sold_individually": false,
        "weight": "",
        "dimensions": {
            "length": "",
            "width": "",
            "height": ""
        },
        "shipping_required": true,
        "shipping_taxable": true,
        "shipping_class": "",
        "shipping_class_id": 0,
        "reviews_allowed": true,
        "average_rating": "0.00",
        "rating_count": 0,
        "related_ids": [
            650,
            1298,
            1312,
            1299,
            1301
        ],
        "upsell_ids": [],
        "cross_sell_ids": [],
        "parent_id": 1311,
        "purchase_note": "",
        "categories": [
            {
                "id": 44,
                "name": "Google Glass",
                "slug": "google-glass"
            },
            {
                "id": 31,
                "name": "Headphone",
                "slug": "headphone"
            },
            {
                "id": 29,
                "name": "Mobile",
                "slug": "mobile"
            },
            {
                "id": 49,
                "name": "Mobile Accessories",
                "slug": "mobile-accessories"
            }
        ],
        "tags": [],
        "images": [
            {
                "id": 1309,
                "date_created": "2018-05-15T16:33:08",
                "date_created_gmt": "2018-05-15T09:33:08",
                "date_modified": "2018-05-15T16:33:08",
                "date_modified_gmt": "2018-05-15T09:33:08",
                "src": "https://wclovers.mstore.io/wp-content/uploads/2018/05/51.png",
                "name": "51",
                "alt": "",
                "position": 0
            },
            {
                "id": 1309,
                "date_created": "2018-05-15T16:33:08",
                "date_created_gmt": "2018-05-15T09:33:08",
                "date_modified": "2018-05-15T16:33:08",
                "date_modified_gmt": "2018-05-15T09:33:08",
                "src": "https://wclovers.mstore.io/wp-content/uploads/2018/05/51.png",
                "name": "51",
                "alt": "",
                "position": 1
            },
            {
                "id": 1308,
                "date_created": "2018-05-15T16:33:06",
                "date_created_gmt": "2018-05-15T09:33:06",
                "date_modified": "2018-05-15T16:33:06",
                "date_modified_gmt": "2018-05-15T09:33:06",
                "src": "https://wclovers.mstore.io/wp-content/uploads/2018/05/50.png",
                "name": "50",
                "alt": "",
                "position": 2
            },
            {
                "id": 646,
                "date_created": "2018-04-30T14:06:31",
                "date_created_gmt": "2018-04-30T07:06:31",
                "date_modified": "2018-04-30T14:06:31",
                "date_modified_gmt": "2018-04-30T07:06:31",
                "src": "https://wclovers.mstore.io/wp-content/uploads/2018/04/Bluetooth-Headsets.jpg",
                "name": "Bluetooth-Headsets",
                "alt": "",
                "position": 3
            }
        ],
        "attributes": [],
        "default_attributes": [],
        "variations": [],
        "grouped_products": [],
        "menu_order": 0,
        "meta_data": [
            {
                "id": 16556,
                "key": "_marketo_deal_date",
                "value": ""
            },
            {
                "id": 16557,
                "key": "_marketo_deal_title",
                "value": ""
            },
            {
                "id": 16558,
                "key": "pageview",
                "value": "24"
            },
            {
                "id": 16559,
                "key": "_wcmp_child_product",
                "value": "1"
            }
        ],
        "store": {
            "vendor_id": "2",
            "vendor_display_name": null,
            "vendor_shop_name": "Test Ven",
            "formatted_display_name": "Test Ven - Test Ven (#2 - test_vendor)",
            "store_hide_email": "no",
            "store_hide_phone": "no",
            "store_hide_address": "no",
            "store_hide_description": "no",
            "store_hide_policy": "no",
            "store_products_per_page": 10,
            "vendor_email": "vendor@demo.com",
            "disable_vendor": false,
            "is_store_offline": "",
            "vendor_shop_logo": "http://wclovers.mstore.io/wp-content/plugins/wc-frontend-manager/assets/images/wcfmmp-blue.png",
            "vendor_banner_type": "image",
            "vendor_banner": "http://wclovers.mstore.io/wp-content/plugins/wc-multivendor-marketplace/assets/images/default_banner.jpg",
            "mobile_banner": "http://wclovers.mstore.io/wp-content/plugins/wc-multivendor-marketplace/assets/images/default_banner.jpg",
            "vendor_list_banner_type": "image",
            "vendor_list_banner": "http://wclovers.mstore.io/wp-content/plugins/wc-multivendor-marketplace/assets/images/default_banner.jpg",
            "store_rating": 5,
            "email_verified": "",
            "vendor_additional_info": [],
            "vendor_description": "",
            "vendor_policies": {
                "shipping_policy_heading": "Shipping Policy",
                "shipping_policy": "<p><br></p>",
                "refund_policy_heading": "Refund Policy",
                "refund_policy": "<p><br></p>",
                "cancellation_policy_heading": "Cancellation / Return / Exchange Policy",
                "cancellation_policy": "<p><br></p>"
            },
            "store_tab_headings": {
                "products": "Products",
                "about": "About",
                "policies": "Policies",
                "reviews": "Reviews (<span class=\"wcfm_reviews_count\">2</span>)",
                "followers": "Followers (<span class=\"wcfm_followers_count\">1</span>)"
            },
            "settings": null
        },
        "is_purchased": false,
        "attributesData": [],
        "product_units": {
            "weight_unit": "oz",
            "dimension_unit": "in"
        },
        "wcfm_product_policy_data": {
            "visible": true,
            "shipping_policy": "<p><br></p>",
            "shipping_policy_heading": "Shipping Policy",
            "refund_policy": "<p><br></p>",
            "refund_policy_heading": "Refund Policy",
            "cancellation_policy": "<p><br></p>",
            "cancellation_policy_heading": "Cancellation / Return / Exchange Policy",
            "tab_title": "Store Policies"
        },
        "showAdditionalInfoTab": false,
        "_links": {
            "self": [
                {
                    "href": "https://wclovers.mstore.io/wp-json/wc/v2/products/2207"
                }
            ],
            "collection": [
                {
                    "href": "https://wclovers.mstore.io/wp-json/wc/v2/products"
                }
            ],
            "up": [
                {
                    "href": "https://wclovers.mstore.io/wp-json/wc/v2/products/1311"
                }
            ]
        }
    },
    {
        "id": 2185,
        "name": "Headset for Phones",
        "slug": "headset-for-phones-2",
        "permalink": "https://wclovers.mstore.io/product/headset-for-phones-2/",
        "date_created": "2018-08-17T17:28:07",
        "date_created_gmt": "2018-08-17T10:28:07",
        "date_modified": "2021-01-12T11:10:47",
        "date_modified_gmt": "2021-01-12T04:10:47",
        "type": "simple",
        "status": "publish",
        "featured": false,
        "catalog_visibility": "visible",
        "description": "<p>Donec pede justo, fringilla vel, aliquet nec, vulputate eget, arcu. In enim justo, rhoncus ut, imperdiet a, venenatis vitae, justo.</p>\n",
        "short_description": "<p>Donec pede justo, fringilla vel, aliquet nec, vulputate eget, arcu. In enim justo, rhoncus ut, imperdiet a, venenatis vitae, justo.</p>\n",
        "sku": "",
        "price": "67",
        "regular_price": "67",
        "sale_price": "",
        "date_on_sale_from": null,
        "date_on_sale_from_gmt": null,
        "date_on_sale_to": null,
        "date_on_sale_to_gmt": null,
        "price_html": "<span class=\"woocommerce-Price-amount amount\"><span class=\"woocommerce-Price-currencySymbol\">&#36;</span>67.00</span>",
        "on_sale": false,
        "purchasable": true,
        "total_sales": 3,
        "virtual": false,
        "downloadable": false,
        "downloads": [],
        "download_limit": -1,
        "download_expiry": -1,
        "external_url": "",
        "button_text": "",
        "tax_status": "taxable",
        "tax_class": "",
        "manage_stock": true,
        "stock_quantity": 33,
        "in_stock": true,
        "backorders": "no",
        "backorders_allowed": false,
        "backordered": false,
        "sold_individually": false,
        "weight": "",
        "dimensions": {
            "length": "",
            "width": "",
            "height": ""
        },
        "shipping_required": true,
        "shipping_taxable": true,
        "shipping_class": "",
        "shipping_class_id": 0,
        "reviews_allowed": true,
        "average_rating": "0.00",
        "rating_count": 0,
        "related_ids": [
            1311,
            1320,
            19,
            2194,
            1332
        ],
        "upsell_ids": [],
        "cross_sell_ids": [],
        "parent_id": 1311,
        "purchase_note": "",
        "categories": [
            {
                "id": 43,
                "name": "Bluetooth",
                "slug": "bluetooth"
            },
            {
                "id": 31,
                "name": "Headphone",
                "slug": "headphone"
            },
            {
                "id": 29,
                "name": "Mobile",
                "slug": "mobile"
            },
            {
                "id": 49,
                "name": "Mobile Accessories",
                "slug": "mobile-accessories"
            }
        ],
        "tags": [],
        "images": [
            {
                "id": 1309,
                "date_created": "2018-05-15T16:33:08",
                "date_created_gmt": "2018-05-15T09:33:08",
                "date_modified": "2018-05-15T16:33:08",
                "date_modified_gmt": "2018-05-15T09:33:08",
                "src": "https://wclovers.mstore.io/wp-content/uploads/2018/05/51.png",
                "name": "51",
                "alt": "",
                "position": 0
            },
            {
                "id": 1309,
                "date_created": "2018-05-15T16:33:08",
                "date_created_gmt": "2018-05-15T09:33:08",
                "date_modified": "2018-05-15T16:33:08",
                "date_modified_gmt": "2018-05-15T09:33:08",
                "src": "https://wclovers.mstore.io/wp-content/uploads/2018/05/51.png",
                "name": "51",
                "alt": "",
                "position": 1
            },
            {
                "id": 1308,
                "date_created": "2018-05-15T16:33:06",
                "date_created_gmt": "2018-05-15T09:33:06",
                "date_modified": "2018-05-15T16:33:06",
                "date_modified_gmt": "2018-05-15T09:33:06",
                "src": "https://wclovers.mstore.io/wp-content/uploads/2018/05/50.png",
                "name": "50",
                "alt": "",
                "position": 2
            },
            {
                "id": 646,
                "date_created": "2018-04-30T14:06:31",
                "date_created_gmt": "2018-04-30T07:06:31",
                "date_modified": "2018-04-30T14:06:31",
                "date_modified_gmt": "2018-04-30T07:06:31",
                "src": "https://wclovers.mstore.io/wp-content/uploads/2018/04/Bluetooth-Headsets.jpg",
                "name": "Bluetooth-Headsets",
                "alt": "",
                "position": 3
            }
        ],
        "attributes": [],
        "default_attributes": [],
        "variations": [],
        "grouped_products": [],
        "menu_order": 0,
        "meta_data": [
            {
                "id": 16049,
                "key": "_marketo_deal_date",
                "value": ""
            },
            {
                "id": 16050,
                "key": "_marketo_deal_title",
                "value": ""
            },
            {
                "id": 16051,
                "key": "pageview",
                "value": "24"
            },
            {
                "id": 16052,
                "key": "_wcmp_child_product",
                "value": "1"
            },
            {
                "id": 16055,
                "key": "slide_template",
                "value": "default"
            },
            {
                "id": 16056,
                "key": "_wcmp_cancallation_policy",
                "value": ""
            },
            {
                "id": 16057,
                "key": "_wcmp_refund_policy",
                "value": ""
            },
            {
                "id": 16058,
                "key": "_wcmp_shipping_policy",
                "value": ""
            },
            {
                "id": 16893,
                "key": "_wcfm_product_views",
                "value": "506"
            }
        ],
        "store": {
            "vendor_id": "2",
            "vendor_display_name": null,
            "vendor_shop_name": "Test Ven",
            "formatted_display_name": "Test Ven - Test Ven (#2 - test_vendor)",
            "store_hide_email": "no",
            "store_hide_phone": "no",
            "store_hide_address": "no",
            "store_hide_description": "no",
            "store_hide_policy": "no",
            "store_products_per_page": 10,
            "vendor_email": "vendor@demo.com",
            "disable_vendor": false,
            "is_store_offline": "",
            "vendor_shop_logo": "http://wclovers.mstore.io/wp-content/plugins/wc-frontend-manager/assets/images/wcfmmp-blue.png",
            "vendor_banner_type": "image",
            "vendor_banner": "http://wclovers.mstore.io/wp-content/plugins/wc-multivendor-marketplace/assets/images/default_banner.jpg",
            "mobile_banner": "http://wclovers.mstore.io/wp-content/plugins/wc-multivendor-marketplace/assets/images/default_banner.jpg",
            "vendor_list_banner_type": "image",
            "vendor_list_banner": "http://wclovers.mstore.io/wp-content/plugins/wc-multivendor-marketplace/assets/images/default_banner.jpg",
            "store_rating": 5,
            "email_verified": "",
            "vendor_additional_info": [],
            "vendor_description": "",
            "vendor_policies": {
                "shipping_policy_heading": "Shipping Policy",
                "shipping_policy": "<p><br></p>",
                "refund_policy_heading": "Refund Policy",
                "refund_policy": "<p><br></p>",
                "cancellation_policy_heading": "Cancellation / Return / Exchange Policy",
                "cancellation_policy": "<p><br></p>"
            },
            "store_tab_headings": {
                "products": "Products",
                "about": "About",
                "policies": "Policies",
                "reviews": "Reviews (<span class=\"wcfm_reviews_count\">2</span>)",
                "followers": "Followers (<span class=\"wcfm_followers_count\">1</span>)"
            },
            "settings": null
        },
        "is_purchased": false,
        "attributesData": [],
        "product_units": {
            "weight_unit": "oz",
            "dimension_unit": "in"
        },
        "wcfm_product_policy_data": {
            "visible": true,
            "shipping_policy": "<p><br></p>",
            "shipping_policy_heading": "Shipping Policy",
            "refund_policy": "<p><br></p>",
            "refund_policy_heading": "Refund Policy",
            "cancellation_policy": "<p><br></p>",
            "cancellation_policy_heading": "Cancellation / Return / Exchange Policy",
            "tab_title": "Store Policies"
        },
        "showAdditionalInfoTab": false,
        "_links": {
            "self": [
                {
                    "href": "https://wclovers.mstore.io/wp-json/wc/v2/products/2185"
                }
            ],
            "collection": [
                {
                    "href": "https://wclovers.mstore.io/wp-json/wc/v2/products"
                }
            ],
            "up": [
                {
                    "href": "https://wclovers.mstore.io/wp-json/wc/v2/products/1311"
                }
            ]
        }
    },
    {
        "id": 2209,
        "name": "Mens Watches",
        "slug": "mens-watches-2",
        "permalink": "https://wclovers.mstore.io/product/mens-watches-2/",
        "date_created": "2018-08-17T10:52:56",
        "date_created_gmt": "2018-08-17T03:52:56",
        "date_modified": "2020-12-29T11:13:52",
        "date_modified_gmt": "2020-12-29T04:13:52",
        "type": "simple",
        "status": "publish",
        "featured": false,
        "catalog_visibility": "visible",
        "description": "<p>Pellentesque habitant morbi tristique senectus et netus et malesuada fames ac turpis egestas. Vestibulum tortor quam, feugiat vitae, ultricies eget, tempor sit amet, ante. Donec eu libero sit amet quam egestas semper. Aenean ultricies mi vitae est. Mauris placerat eleifend leo.</p>\n",
        "short_description": "<p>Pellentesque habitant morbi tristique senectus et netus et malesuada fames ac turpis egestas. Vestibulum tortor quam, feugiat vitae, ultricies eget, tempor sit amet, ante. Donec eu libero sit amet quam egestas semper. Aenean ultricies mi vitae est. Mauris placerat eleifend leo.</p>\n",
        "sku": "",
        "price": "80",
        "regular_price": "100",
        "sale_price": "80",
        "date_on_sale_from": null,
        "date_on_sale_from_gmt": null,
        "date_on_sale_to": null,
        "date_on_sale_to_gmt": null,
        "price_html": "<del><span class=\"woocommerce-Price-amount amount\"><span class=\"woocommerce-Price-currencySymbol\">&#36;</span>100.00</span></del> <ins><span class=\"woocommerce-Price-amount amount\"><span class=\"woocommerce-Price-currencySymbol\">&#36;</span>80.00</span></ins>",
        "on_sale": true,
        "purchasable": true,
        "total_sales": 38,
        "virtual": false,
        "downloadable": false,
        "downloads": [],
        "download_limit": -1,
        "download_expiry": -1,
        "external_url": "",
        "button_text": "",
        "tax_status": "taxable",
        "tax_class": "",
        "manage_stock": false,
        "stock_quantity": null,
        "in_stock": false,
        "backorders": "no",
        "backorders_allowed": false,
        "backordered": false,
        "sold_individually": false,
        "weight": "",
        "dimensions": {
            "length": "",
            "width": "",
            "height": ""
        },
        "shipping_required": true,
        "shipping_taxable": true,
        "shipping_class": "",
        "shipping_class_id": 0,
        "reviews_allowed": true,
        "average_rating": "0.00",
        "rating_count": 0,
        "related_ids": [
            3285,
            2196,
            1334,
            1295,
            2200
        ],
        "upsell_ids": [],
        "cross_sell_ids": [
            15
        ],
        "parent_id": 60,
        "purchase_note": "",
        "categories": [
            {
                "id": 38,
                "name": "3d Glass",
                "slug": "3d-glass"
            },
            {
                "id": 64,
                "name": "Accessories",
                "slug": "accessories"
            },
            {
                "id": 32,
                "name": "Camera",
                "slug": "camera"
            },
            {
                "id": 50,
                "name": "Computer Accessories",
                "slug": "computer-accessories"
            }
        ],
        "tags": [
            {
                "id": 88,
                "name": "banner",
                "slug": "banner"
            }
        ],
        "images": [
            {
                "id": 3261,
                "date_created": "2020-12-29T18:11:45",
                "date_created_gmt": "2020-12-29T04:11:45",
                "date_modified": "2020-12-29T18:13:52",
                "date_modified_gmt": "2020-12-29T04:13:52",
                "src": "https://wclovers.mstore.io/wp-content/uploads/2020/12/Mens-Watches.jpg",
                "name": "Mens-Watches",
                "alt": "",
                "position": 0
            },
            {
                "id": 3262,
                "date_created": "2020-12-29T18:12:14",
                "date_created_gmt": "2020-12-29T04:12:14",
                "date_modified": "2020-12-29T18:13:52",
                "date_modified_gmt": "2020-12-29T04:13:52",
                "src": "https://wclovers.mstore.io/wp-content/uploads/2020/12/Luxury-Digital-Male-Sport-Watch-Waterproof-100x100-1.jpg",
                "name": "Luxury-Digital-Male-Sport-Watch-Waterproof-100&#215;100",
                "alt": "",
                "position": 1
            },
            {
                "id": 3266,
                "date_created": "2020-12-29T18:12:20",
                "date_created_gmt": "2020-12-29T04:12:20",
                "date_modified": "2020-12-29T18:13:52",
                "date_modified_gmt": "2020-12-29T04:13:52",
                "src": "https://wclovers.mstore.io/wp-content/uploads/2020/12/Xiaomi-Mijia-PM2-5-Detector-Xiaomi-OLED-Screen-Smart-Sensor-Adapt-Mi-100x100-1.jpg",
                "name": "Xiaomi-Mijia-PM2-5-Detector-Xiaomi-OLED-Screen-Smart-Sensor-Adapt-Mi-100&#215;100",
                "alt": "",
                "position": 2
            },
            {
                "id": 3265,
                "date_created": "2020-12-29T18:12:18",
                "date_created_gmt": "2020-12-29T04:12:18",
                "date_modified": "2020-12-29T18:13:52",
                "date_modified_gmt": "2020-12-29T04:13:52",
                "src": "https://wclovers.mstore.io/wp-content/uploads/2020/12/Screen-Smart-Sensor-Adapt-Mi-100x100-1.jpg",
                "name": "Screen-Smart-Sensor-Adapt-Mi-100&#215;100",
                "alt": "",
                "position": 3
            },
            {
                "id": 3263,
                "date_created": "2020-12-29T18:12:15",
                "date_created_gmt": "2020-12-29T04:12:15",
                "date_modified": "2020-12-29T18:13:52",
                "date_modified_gmt": "2020-12-29T04:13:52",
                "src": "https://wclovers.mstore.io/wp-content/uploads/2020/12/Mens-Watches-100x100-1.jpg",
                "name": "Mens-Watches-100&#215;100",
                "alt": "",
                "position": 4
            }
        ],
        "attributes": [],
        "default_attributes": [],
        "variations": [],
        "grouped_products": [],
        "menu_order": 0,
        "meta_data": [
            {
                "id": 16599,
                "key": "_marketo_deal_date",
                "value": ""
            },
            {
                "id": 16600,
                "key": "_marketo_deal_title",
                "value": ""
            },
            {
                "id": 16601,
                "key": "pageview",
                "value": "5"
            },
            {
                "id": 16602,
                "key": "_wcmp_child_product",
                "value": "1"
            },
            {
                "id": 16605,
                "key": "slide_template",
                "value": ""
            },
            {
                "id": 16606,
                "key": "_wcmp_cancallation_policy",
                "value": ""
            },
            {
                "id": 16607,
                "key": "_wcmp_refund_policy",
                "value": ""
            },
            {
                "id": 16608,
                "key": "_wcmp_shipping_policy",
                "value": ""
            },
            {
                "id": 16892,
                "key": "_wcfm_product_views",
                "value": "402"
            },
            {
                "id": 31184,
                "key": "_catalog",
                "value": "no"
            },
            {
                "id": 31185,
                "key": "disable_add_to_cart",
                "value": "no"
            },
            {
                "id": 31186,
                "key": "disable_price",
                "value": "no"
            },
            {
                "id": 31187,
                "key": "_wcfmmp_processing_time",
                "value": ""
            },
            {
                "id": 31188,
                "key": "wcfm_policy_product_options",
                "value": {
                    "0": "",
                    "shipping_policy": "<p><br></p>",
                    "refund_policy": "<p><br></p>",
                    "cancellation_policy": "<p><br></p>"
                }
            },
            {
                "id": 31189,
                "key": "_wcfmmp_commission",
                "value": {
                    "commission_mode": "global",
                    "commission_percent": "90",
                    "commission_fixed": "",
                    "tax_name": "",
                    "tax_percent": ""
                }
            }
        ],
        "store": {
            "vendor_id": "2",
            "vendor_display_name": null,
            "vendor_shop_name": "Test Ven",
            "formatted_display_name": "Test Ven - Test Ven (#2 - test_vendor)",
            "store_hide_email": "no",
            "store_hide_phone": "no",
            "store_hide_address": "no",
            "store_hide_description": "no",
            "store_hide_policy": "no",
            "store_products_per_page": 10,
            "vendor_email": "vendor@demo.com",
            "disable_vendor": false,
            "is_store_offline": "",
            "vendor_shop_logo": "http://wclovers.mstore.io/wp-content/plugins/wc-frontend-manager/assets/images/wcfmmp-blue.png",
            "vendor_banner_type": "image",
            "vendor_banner": "http://wclovers.mstore.io/wp-content/plugins/wc-multivendor-marketplace/assets/images/default_banner.jpg",
            "mobile_banner": "http://wclovers.mstore.io/wp-content/plugins/wc-multivendor-marketplace/assets/images/default_banner.jpg",
            "vendor_list_banner_type": "image",
            "vendor_list_banner": "http://wclovers.mstore.io/wp-content/plugins/wc-multivendor-marketplace/assets/images/default_banner.jpg",
            "store_rating": 5,
            "email_verified": "",
            "vendor_additional_info": [],
            "vendor_description": "",
            "vendor_policies": {
                "shipping_policy_heading": "Shipping Policy",
                "shipping_policy": "<p><br></p>",
                "refund_policy_heading": "Refund Policy",
                "refund_policy": "<p><br></p>",
                "cancellation_policy_heading": "Cancellation / Return / Exchange Policy",
                "cancellation_policy": "<p><br></p>"
            },
            "store_tab_headings": {
                "products": "Products",
                "about": "About",
                "policies": "Policies",
                "reviews": "Reviews (<span class=\"wcfm_reviews_count\">2</span>)",
                "followers": "Followers (<span class=\"wcfm_followers_count\">1</span>)"
            },
            "settings": null
        },
        "is_purchased": false,
        "attributesData": [],
        "product_units": {
            "weight_unit": "oz",
            "dimension_unit": "in"
        },
        "wcfm_product_policy_data": {
            "visible": true,
            "shipping_policy": "<p><br></p>",
            "shipping_policy_heading": "Shipping Policy",
            "refund_policy": "<p><br></p>",
            "refund_policy_heading": "Refund Policy",
            "cancellation_policy": "<p><br></p>",
            "cancellation_policy_heading": "Cancellation / Return / Exchange Policy",
            "tab_title": "Store Policies"
        },
        "showAdditionalInfoTab": false,
        "_links": {
            "self": [
                {
                    "href": "https://wclovers.mstore.io/wp-json/wc/v2/products/2209"
                }
            ],
            "collection": [
                {
                    "href": "https://wclovers.mstore.io/wp-json/wc/v2/products"
                }
            ],
            "up": [
                {
                    "href": "https://wclovers.mstore.io/wp-json/wc/v2/products/60"
                }
            ]
        }
    },
    {
        "id": 2202,
        "name": "Golden Bluetooth",
        "slug": "golden-bluetooth-2",
        "permalink": "https://wclovers.mstore.io/product/golden-bluetooth-2/",
        "date_created": "2018-08-17T17:47:24",
        "date_created_gmt": "2018-08-17T10:47:24",
        "date_modified": "2021-01-10T06:45:44",
        "date_modified_gmt": "2021-01-09T23:45:44",
        "type": "simple",
        "status": "publish",
        "featured": true,
        "catalog_visibility": "visible",
        "description": "<p>Pellentesque habitant morbi tristique senectus et netus et malesuada fames ac turpis egestas. Vestibulum tortor quam, feugiat vitae, ultricies eget, tempor sit amet, ante. Donec eu libero sit amet quam egestas semper. Aenean ultricies mi vitae est. Mauris placerat eleifend leo.</p>\n",
        "short_description": "<p>Pellentesque habitant morbi tristique senectus et netus et malesuada fames ac turpis egestas. Vestibulum tortor quam, feugiat vitae, ultricies eget, tempor sit amet, ante. Donec eu libero sit amet quam egestas semper. Aenean ultricies mi vitae est. Mauris placerat eleifend leo.</p>\n",
        "sku": "",
        "price": "12",
        "regular_price": "23",
        "sale_price": "12",
        "date_on_sale_from": null,
        "date_on_sale_from_gmt": null,
        "date_on_sale_to": null,
        "date_on_sale_to_gmt": null,
        "price_html": "<del><span class=\"woocommerce-Price-amount amount\"><span class=\"woocommerce-Price-currencySymbol\">&#36;</span>23.00</span></del> <ins><span class=\"woocommerce-Price-amount amount\"><span class=\"woocommerce-Price-currencySymbol\">&#36;</span>12.00</span></ins>",
        "on_sale": true,
        "purchasable": true,
        "total_sales": 1,
        "virtual": false,
        "downloadable": false,
        "downloads": [],
        "download_limit": -1,
        "download_expiry": -1,
        "external_url": "",
        "button_text": "",
        "tax_status": "taxable",
        "tax_class": "",
        "manage_stock": true,
        "stock_quantity": 18,
        "in_stock": true,
        "backorders": "no",
        "backorders_allowed": false,
        "backordered": false,
        "sold_individually": false,
        "weight": "",
        "dimensions": {
            "length": "",
            "width": "",
            "height": ""
        },
        "shipping_required": true,
        "shipping_taxable": true,
        "shipping_class": "",
        "shipping_class_id": 0,
        "reviews_allowed": true,
        "average_rating": "0.00",
        "rating_count": 0,
        "related_ids": [
            599,
            2200,
            653,
            649,
            37
        ],
        "upsell_ids": [],
        "cross_sell_ids": [],
        "parent_id": 644,
        "purchase_note": "",
        "categories": [
            {
                "id": 31,
                "name": "Headphone",
                "slug": "headphone"
            }
        ],
        "tags": [],
        "images": [
            {
                "id": 648,
                "date_created": "2018-04-30T14:06:34",
                "date_created_gmt": "2018-04-30T07:06:34",
                "date_modified": "2018-04-30T14:06:34",
                "date_modified_gmt": "2018-04-30T07:06:34",
                "src": "https://wclovers.mstore.io/wp-content/uploads/2018/04/Headphones-Wireless-Stereo-Headsets-earbuds-with-Mic.jpg",
                "name": "Headphones-Wireless-Stereo-Headsets-earbuds-with-Mic",
                "alt": "",
                "position": 0
            },
            {
                "id": 646,
                "date_created": "2018-04-30T14:06:31",
                "date_created_gmt": "2018-04-30T07:06:31",
                "date_modified": "2018-04-30T14:06:31",
                "date_modified_gmt": "2018-04-30T07:06:31",
                "src": "https://wclovers.mstore.io/wp-content/uploads/2018/04/Bluetooth-Headsets.jpg",
                "name": "Bluetooth-Headsets",
                "alt": "",
                "position": 1
            },
            {
                "id": 645,
                "date_created": "2018-04-30T14:06:29",
                "date_created_gmt": "2018-04-30T07:06:29",
                "date_modified": "2018-04-30T14:06:29",
                "date_modified_gmt": "2018-04-30T07:06:29",
                "src": "https://wclovers.mstore.io/wp-content/uploads/2018/04/Bluetooth-Headphones-Wireless-Stereo-Headset.jpg",
                "name": "Bluetooth-Headphones-Wireless-Stereo-Headset",
                "alt": "",
                "position": 2
            },
            {
                "id": 495,
                "date_created": "2018-04-26T13:20:42",
                "date_created_gmt": "2018-04-26T06:20:42",
                "date_modified": "2018-04-26T13:20:42",
                "date_modified_gmt": "2018-04-26T06:20:42",
                "src": "https://wclovers.mstore.io/wp-content/uploads/2013/06/DEEP-BASS-Headphones-Earphones-3-5mm-AUX-Foldable-Portable-Adjustable-Gaming-Headset-For-Phones-MP3-MP4-1.jpg",
                "name": "DEEP-BASS-Headphones-Earphones-3-5mm-AUX-Foldable-Portable-Adjustable-Gaming-Headset-For-Phones-MP3-MP4 (1)",
                "alt": "",
                "position": 3
            }
        ],
        "attributes": [],
        "default_attributes": [],
        "variations": [],
        "grouped_products": [],
        "menu_order": 0,
        "meta_data": [
            {
                "id": 16445,
                "key": "_marketo_deal_date",
                "value": "2018-10-28"
            },
            {
                "id": 16446,
                "key": "_marketo_deal_title",
                "value": "<span class=\"color-primary\">Hurry up!</span> Offers ends in:"
            },
            {
                "id": 16447,
                "key": "pageview",
                "value": "6"
            },
            {
                "id": 16448,
                "key": "_wcmp_child_product",
                "value": "1"
            },
            {
                "id": 16451,
                "key": "slide_template",
                "value": "default"
            },
            {
                "id": 16452,
                "key": "_wcmp_cancallation_policy",
                "value": ""
            },
            {
                "id": 16453,
                "key": "_wcmp_refund_policy",
                "value": ""
            },
            {
                "id": 16454,
                "key": "_wcmp_shipping_policy",
                "value": ""
            },
            {
                "id": 16896,
                "key": "_wcfm_product_views",
                "value": "467"
            }
        ],
        "store": {
            "vendor_id": "2",
            "vendor_display_name": null,
            "vendor_shop_name": "Test Ven",
            "formatted_display_name": "Test Ven - Test Ven (#2 - test_vendor)",
            "store_hide_email": "no",
            "store_hide_phone": "no",
            "store_hide_address": "no",
            "store_hide_description": "no",
            "store_hide_policy": "no",
            "store_products_per_page": 10,
            "vendor_email": "vendor@demo.com",
            "disable_vendor": false,
            "is_store_offline": "",
            "vendor_shop_logo": "http://wclovers.mstore.io/wp-content/plugins/wc-frontend-manager/assets/images/wcfmmp-blue.png",
            "vendor_banner_type": "image",
            "vendor_banner": "http://wclovers.mstore.io/wp-content/plugins/wc-multivendor-marketplace/assets/images/default_banner.jpg",
            "mobile_banner": "http://wclovers.mstore.io/wp-content/plugins/wc-multivendor-marketplace/assets/images/default_banner.jpg",
            "vendor_list_banner_type": "image",
            "vendor_list_banner": "http://wclovers.mstore.io/wp-content/plugins/wc-multivendor-marketplace/assets/images/default_banner.jpg",
            "store_rating": 5,
            "email_verified": "",
            "vendor_additional_info": [],
            "vendor_description": "",
            "vendor_policies": {
                "shipping_policy_heading": "Shipping Policy",
                "shipping_policy": "<p><br></p>",
                "refund_policy_heading": "Refund Policy",
                "refund_policy": "<p><br></p>",
                "cancellation_policy_heading": "Cancellation / Return / Exchange Policy",
                "cancellation_policy": "<p><br></p>"
            },
            "store_tab_headings": {
                "products": "Products",
                "about": "About",
                "policies": "Policies",
                "reviews": "Reviews (<span class=\"wcfm_reviews_count\">2</span>)",
                "followers": "Followers (<span class=\"wcfm_followers_count\">1</span>)"
            },
            "settings": null
        },
        "is_purchased": false,
        "attributesData": [],
        "product_units": {
            "weight_unit": "oz",
            "dimension_unit": "in"
        },
        "wcfm_product_policy_data": {
            "visible": true,
            "shipping_policy": "<p><br></p>",
            "shipping_policy_heading": "Shipping Policy",
            "refund_policy": "<p><br></p>",
            "refund_policy_heading": "Refund Policy",
            "cancellation_policy": "<p><br></p>",
            "cancellation_policy_heading": "Cancellation / Return / Exchange Policy",
            "tab_title": "Store Policies"
        },
        "showAdditionalInfoTab": false,
        "_links": {
            "self": [
                {
                    "href": "https://wclovers.mstore.io/wp-json/wc/v2/products/2202"
                }
            ],
            "collection": [
                {
                    "href": "https://wclovers.mstore.io/wp-json/wc/v2/products"
                }
            ],
            "up": [
                {
                    "href": "https://wclovers.mstore.io/wp-json/wc/v2/products/644"
                }
            ]
        }
    },
    {
        "id": 2200,
        "name": "Bluetooth Speaker",
        "slug": "bluetooth-speaker-2",
        "permalink": "https://wclovers.mstore.io/product/bluetooth-speaker-2/",
        "date_created": "2018-08-17T17:46:44",
        "date_created_gmt": "2018-08-17T10:46:44",
        "date_modified": "2021-01-12T05:13:20",
        "date_modified_gmt": "2021-01-11T22:13:20",
        "type": "variable",
        "status": "publish",
        "featured": true,
        "catalog_visibility": "visible",
        "description": "<p>Lorem ipsum dolor sit amet, consectetuer adipiscing elit. Aenean commodo ligula eget dolor. Aenean massa. Cum sociis natoque penatibus et magnis dis parturient montes, nascetur ridiculus mus.</p>\n<p>Donec quam felis, ultricies nec, pellentesque eu, pretium quis, sem. Nulla consequat massa quis enim. Donec pede justo, fringilla vel, aliquet nec, vulputate eget, arcu. In enim justo, rhoncus ut, imperdiet a, venenatis vitae, justo.</p>\n",
        "short_description": "",
        "sku": "",
        "price": "87",
        "regular_price": "",
        "sale_price": "",
        "date_on_sale_from": null,
        "date_on_sale_from_gmt": null,
        "date_on_sale_to": null,
        "date_on_sale_to_gmt": null,
        "price_html": "<span class=\"woocommerce-Price-amount amount\"><span class=\"woocommerce-Price-currencySymbol\">&#36;</span>87.00</span> &ndash; <span class=\"woocommerce-Price-amount amount\"><span class=\"woocommerce-Price-currencySymbol\">&#36;</span>120.00</span>",
        "on_sale": false,
        "purchasable": true,
        "total_sales": 35,
        "virtual": false,
        "downloadable": false,
        "downloads": [],
        "download_limit": -1,
        "download_expiry": -1,
        "external_url": "",
        "button_text": "",
        "tax_status": "taxable",
        "tax_class": "",
        "manage_stock": true,
        "stock_quantity": 1,
        "in_stock": true,
        "backorders": "no",
        "backorders_allowed": false,
        "backordered": false,
        "sold_individually": false,
        "weight": "",
        "dimensions": {
            "length": "",
            "width": "",
            "height": ""
        },
        "shipping_required": true,
        "shipping_taxable": true,
        "shipping_class": "",
        "shipping_class_id": 0,
        "reviews_allowed": true,
        "average_rating": "0.00",
        "rating_count": 0,
        "related_ids": [
            2187,
            2202,
            653,
            67,
            643
        ],
        "upsell_ids": [],
        "cross_sell_ids": [],
        "parent_id": 0,
        "purchase_note": "",
        "categories": [
            {
                "id": 32,
                "name": "Camera",
                "slug": "camera"
            },
            {
                "id": 31,
                "name": "Headphone",
                "slug": "headphone"
            },
            {
                "id": 41,
                "name": "Speaker",
                "slug": "speaker"
            }
        ],
        "tags": [],
        "images": [
            {
                "id": 594,
                "date_created": "2018-04-30T12:26:55",
                "date_created_gmt": "2018-04-30T05:26:55",
                "date_modified": "2018-04-30T12:26:55",
                "date_modified_gmt": "2018-04-30T05:26:55",
                "src": "https://wclovers.mstore.io/wp-content/uploads/2013/06/HTB1olbtmlDH8KJj.jpg",
                "name": "HTB1olbtmlDH8KJj",
                "alt": "",
                "position": 0
            },
            {
                "id": 592,
                "date_created": "2018-04-30T12:25:52",
                "date_created_gmt": "2018-04-30T05:25:52",
                "date_modified": "2018-04-30T12:25:52",
                "date_modified_gmt": "2018-04-30T05:25:52",
                "src": "https://wclovers.mstore.io/wp-content/uploads/2013/06/LEICKE-Bluetooth-Portable-Speaker.jpg",
                "name": "LEICKE-Bluetooth-Portable-Speaker",
                "alt": "",
                "position": 1
            },
            {
                "id": 596,
                "date_created": "2018-04-30T12:26:58",
                "date_created_gmt": "2018-04-30T05:26:58",
                "date_modified": "2018-04-30T12:26:58",
                "date_modified_gmt": "2018-04-30T05:26:58",
                "src": "https://wclovers.mstore.io/wp-content/uploads/2013/06/Wireless-Speaker-Portable-bluetooth.jpg",
                "name": "Wireless-Speaker-Portable-bluetooth",
                "alt": "",
                "position": 2
            }
        ],
        "attributes": [
            {
                "id": 1,
                "name": "color",
                "position": 0,
                "visible": true,
                "variation": true,
                "options": [
                    "Black",
                    "Blue",
                    "Green"
                ]
            }
        ],
        "default_attributes": [],
        "variations": [
            2809,
            2807
        ],
        "grouped_products": [],
        "menu_order": 0,
        "meta_data": [
            {
                "id": 16397,
                "key": "_marketo_deal_date",
                "value": ""
            },
            {
                "id": 16398,
                "key": "_marketo_deal_title",
                "value": ""
            },
            {
                "id": 16399,
                "key": "pageview",
                "value": "12"
            },
            {
                "id": 16400,
                "key": "_wcmp_child_product",
                "value": "1"
            },
            {
                "id": 16403,
                "key": "slide_template",
                "value": "default"
            },
            {
                "id": 16404,
                "key": "_wcmp_cancallation_policy",
                "value": ""
            },
            {
                "id": 16405,
                "key": "_wcmp_refund_policy",
                "value": ""
            },
            {
                "id": 16406,
                "key": "_wcmp_shipping_policy",
                "value": ""
            },
            {
                "id": 16904,
                "key": "_wcfm_product_views",
                "value": "546"
            },
            {
                "id": 23575,
                "key": "_wcfm_product_approved_notified",
                "value": "yes"
            },
            {
                "id": 23577,
                "key": "_wcfmmp_commission",
                "value": {
                    "commission_mode": "global",
                    "commission_percent": "90",
                    "commission_fixed": "",
                    "tax_name": "",
                    "tax_percent": ""
                }
            }
        ],
        "store": {
            "vendor_id": "2",
            "vendor_display_name": null,
            "vendor_shop_name": "Test Ven",
            "formatted_display_name": "Test Ven - Test Ven (#2 - test_vendor)",
            "store_hide_email": "no",
            "store_hide_phone": "no",
            "store_hide_address": "no",
            "store_hide_description": "no",
            "store_hide_policy": "no",
            "store_products_per_page": 10,
            "vendor_email": "vendor@demo.com",
            "disable_vendor": false,
            "is_store_offline": "",
            "vendor_shop_logo": "http://wclovers.mstore.io/wp-content/plugins/wc-frontend-manager/assets/images/wcfmmp-blue.png",
            "vendor_banner_type": "image",
            "vendor_banner": "http://wclovers.mstore.io/wp-content/plugins/wc-multivendor-marketplace/assets/images/default_banner.jpg",
            "mobile_banner": "http://wclovers.mstore.io/wp-content/plugins/wc-multivendor-marketplace/assets/images/default_banner.jpg",
            "vendor_list_banner_type": "image",
            "vendor_list_banner": "http://wclovers.mstore.io/wp-content/plugins/wc-multivendor-marketplace/assets/images/default_banner.jpg",
            "store_rating": 5,
            "email_verified": "",
            "vendor_additional_info": [],
            "vendor_description": "",
            "vendor_policies": {
                "shipping_policy_heading": "Shipping Policy",
                "shipping_policy": "<p><br></p>",
                "refund_policy_heading": "Refund Policy",
                "refund_policy": "<p><br></p>",
                "cancellation_policy_heading": "Cancellation / Return / Exchange Policy",
                "cancellation_policy": "<p><br></p>"
            },
            "store_tab_headings": {
                "products": "Products",
                "about": "About",
                "policies": "Policies",
                "reviews": "Reviews (<span class=\"wcfm_reviews_count\">2</span>)",
                "followers": "Followers (<span class=\"wcfm_followers_count\">1</span>)"
            },
            "settings": null
        },
        "is_purchased": false,
        "attributesData": [
            {
                "id": 1,
                "name": "pa_color",
                "options": [
                    {
                        "term_id": 16,
                        "name": "Black",
                        "slug": "black",
                        "term_group": 0,
                        "term_taxonomy_id": 16,
                        "taxonomy": "pa_color",
                        "description": "",
                        "parent": 0,
                        "count": 4,
                        "filter": "raw"
                    },
                    {
                        "term_id": 17,
                        "name": "Blue",
                        "slug": "blue",
                        "term_group": 0,
                        "term_taxonomy_id": 17,
                        "taxonomy": "pa_color",
                        "description": "",
                        "parent": 0,
                        "count": 2,
                        "filter": "raw"
                    },
                    {
                        "term_id": 18,
                        "name": "Green",
                        "slug": "green",
                        "term_group": 0,
                        "term_taxonomy_id": 18,
                        "taxonomy": "pa_color",
                        "description": "",
                        "parent": 0,
                        "count": 4,
                        "filter": "raw"
                    }
                ],
                "position": 0,
                "visible": true,
                "variation": true,
                "is_visible": 1,
                "is_variation": 1,
                "is_taxonomy": 1,
                "value": "",
                "label": "color"
            }
        ],
        "product_units": {
            "weight_unit": "oz",
            "dimension_unit": "in"
        },
        "wcfm_product_policy_data": {
            "visible": true,
            "shipping_policy": "<p><br></p>",
            "shipping_policy_heading": "Shipping Policy",
            "refund_policy": "<p><br></p>",
            "refund_policy_heading": "Refund Policy",
            "cancellation_policy": "<p><br></p>",
            "cancellation_policy_heading": "Cancellation / Return / Exchange Policy",
            "tab_title": "Store Policies"
        },
        "showAdditionalInfoTab": true,
        "_links": {
            "self": [
                {
                    "href": "https://wclovers.mstore.io/wp-json/wc/v2/products/2200"
                }
            ],
            "collection": [
                {
                    "href": "https://wclovers.mstore.io/wp-json/wc/v2/products"
                }
            ]
        }
    },
    {
        "id": 2198,
        "name": "3D Glass",
        "slug": "3d-glass-2",
        "permalink": "https://wclovers.mstore.io/product/3d-glass-2/",
        "date_created": "2018-08-17T10:46:23",
        "date_created_gmt": "2018-08-17T03:46:23",
        "date_modified": "2020-12-22T17:06:27",
        "date_modified_gmt": "2020-12-22T10:06:27",
        "type": "simple",
        "status": "publish",
        "featured": true,
        "catalog_visibility": "visible",
        "description": "<p>Pellentesque habitant morbi tristique senectus et netus et malesuada fames ac turpis egestas. Vestibulum tortor quam, feugiat vitae, ultricies eget, tempor sit amet, ante. Donec eu libero sit amet quam egestas semper. Aenean ultricies mi vitae est. Mauris placerat eleifend leo.</p>\n",
        "short_description": "<p>Pellentesque habitant morbi tristique senectus et netus et malesuada fames ac turpis egestas. Vestibulum tortor quam, feugiat vitae, ultricies eget, tempor sit amet, ante. Donec eu libero sit amet quam egestas semper. Aenean ultricies mi vitae est. Mauris placerat eleifend leo.</p>\n",
        "sku": "",
        "price": "540",
        "regular_price": "640",
        "sale_price": "540",
        "date_on_sale_from": null,
        "date_on_sale_from_gmt": null,
        "date_on_sale_to": null,
        "date_on_sale_to_gmt": null,
        "price_html": "<del><span class=\"woocommerce-Price-amount amount\"><span class=\"woocommerce-Price-currencySymbol\">&#36;</span>640.00</span></del> <ins><span class=\"woocommerce-Price-amount amount\"><span class=\"woocommerce-Price-currencySymbol\">&#36;</span>540.00</span></ins>",
        "on_sale": true,
        "purchasable": true,
        "total_sales": 17,
        "virtual": false,
        "downloadable": false,
        "downloads": [],
        "download_limit": -1,
        "download_expiry": -1,
        "external_url": "",
        "button_text": "",
        "tax_status": "taxable",
        "tax_class": "",
        "manage_stock": true,
        "stock_quantity": -1,
        "in_stock": false,
        "backorders": "no",
        "backorders_allowed": false,
        "backordered": false,
        "sold_individually": false,
        "weight": "",
        "dimensions": {
            "length": "",
            "width": "",
            "height": ""
        },
        "shipping_required": true,
        "shipping_taxable": true,
        "shipping_class": "",
        "shipping_class_id": 0,
        "reviews_allowed": true,
        "average_rating": "0.00",
        "rating_count": 0,
        "related_ids": [
            22,
            1334,
            2187,
            2196,
            67
        ],
        "upsell_ids": [
            40
        ],
        "cross_sell_ids": [],
        "parent_id": 22,
        "purchase_note": "",
        "categories": [
            {
                "id": 38,
                "name": "3d Glass",
                "slug": "3d-glass"
            }
        ],
        "tags": [
            {
                "id": 88,
                "name": "banner",
                "slug": "banner"
            }
        ],
        "images": [
            {
                "id": 547,
                "date_created": "2018-04-27T17:41:14",
                "date_created_gmt": "2018-04-27T10:41:14",
                "date_modified": "2018-04-27T17:41:14",
                "date_modified_gmt": "2018-04-27T10:41:14",
                "src": "https://wclovers.mstore.io/wp-content/uploads/2013/06/3D-VR-Glass-Virtual-Reality.jpg",
                "name": "3D-VR-Glass-Virtual-Reality",
                "alt": "",
                "position": 0
            },
            {
                "id": 546,
                "date_created": "2018-04-27T17:41:12",
                "date_created_gmt": "2018-04-27T10:41:12",
                "date_modified": "2018-04-27T17:41:12",
                "date_modified_gmt": "2018-04-27T10:41:12",
                "src": "https://wclovers.mstore.io/wp-content/uploads/2013/06/3D-VR-Glass.jpg",
                "name": "3D-VR-Glass",
                "alt": "",
                "position": 1
            },
            {
                "id": 545,
                "date_created": "2018-04-27T17:41:10",
                "date_created_gmt": "2018-04-27T10:41:10",
                "date_modified": "2018-04-27T17:41:10",
                "date_modified_gmt": "2018-04-27T10:41:10",
                "src": "https://wclovers.mstore.io/wp-content/uploads/2013/06/Glasses-3D-Movies-Games-for.jpg",
                "name": "Glasses-3D-Movies-Games-for",
                "alt": "",
                "position": 2
            },
            {
                "id": 548,
                "date_created": "2018-04-27T17:41:15",
                "date_created_gmt": "2018-04-27T10:41:15",
                "date_modified": "2018-04-27T17:41:15",
                "date_modified_gmt": "2018-04-27T10:41:15",
                "src": "https://wclovers.mstore.io/wp-content/uploads/2013/06/Google-Cardboard-Game-Movie.jpg",
                "name": "Google-Cardboard-Game-Movie",
                "alt": "",
                "position": 3
            }
        ],
        "attributes": [
            {
                "id": 1,
                "name": "color",
                "position": 0,
                "visible": false,
                "variation": true,
                "options": [
                    "Black",
                    "Green"
                ]
            }
        ],
        "default_attributes": [],
        "variations": [],
        "grouped_products": [],
        "menu_order": 0,
        "meta_data": [
            {
                "id": 16341,
                "key": "_min_variation_price",
                "value": "20"
            },
            {
                "id": 16342,
                "key": "_max_variation_price",
                "value": "20"
            },
            {
                "id": 16343,
                "key": "_min_variation_regular_price",
                "value": "20"
            },
            {
                "id": 16344,
                "key": "_max_variation_regular_price",
                "value": "20"
            },
            {
                "id": 16345,
                "key": "_min_variation_sale_price",
                "value": ""
            },
            {
                "id": 16346,
                "key": "_max_variation_sale_price",
                "value": ""
            },
            {
                "id": 16347,
                "key": "_marketpress_deal_date",
                "value": ""
            },
            {
                "id": 16348,
                "key": "_marketpress_deal_title",
                "value": ""
            },
            {
                "id": 16349,
                "key": "_marketo_deal_date",
                "value": "2018-12-30"
            },
            {
                "id": 16350,
                "key": "_marketo_deal_title",
                "value": "<span class=\"color-primary\">Hurry up!</span> Offers ends in:"
            },
            {
                "id": 16351,
                "key": "slide_template",
                "value": ""
            },
            {
                "id": 16352,
                "key": "pageview",
                "value": "28"
            },
            {
                "id": 16353,
                "key": "_wcmp_child_product",
                "value": "1"
            },
            {
                "id": 16356,
                "key": "_wcmp_cancallation_policy",
                "value": ""
            },
            {
                "id": 16357,
                "key": "_wcmp_refund_policy",
                "value": ""
            },
            {
                "id": 16358,
                "key": "_wcmp_shipping_policy",
                "value": ""
            },
            {
                "id": 16916,
                "key": "_wcfm_product_views",
                "value": "452"
            },
            {
                "id": 29493,
                "key": "_is_multi_parent",
                "value": "2198"
            }
        ],
        "store": {
            "vendor_id": "2",
            "vendor_display_name": null,
            "vendor_shop_name": "Test Ven",
            "formatted_display_name": "Test Ven - Test Ven (#2 - test_vendor)",
            "store_hide_email": "no",
            "store_hide_phone": "no",
            "store_hide_address": "no",
            "store_hide_description": "no",
            "store_hide_policy": "no",
            "store_products_per_page": 10,
            "vendor_email": "vendor@demo.com",
            "disable_vendor": false,
            "is_store_offline": "",
            "vendor_shop_logo": "http://wclovers.mstore.io/wp-content/plugins/wc-frontend-manager/assets/images/wcfmmp-blue.png",
            "vendor_banner_type": "image",
            "vendor_banner": "http://wclovers.mstore.io/wp-content/plugins/wc-multivendor-marketplace/assets/images/default_banner.jpg",
            "mobile_banner": "http://wclovers.mstore.io/wp-content/plugins/wc-multivendor-marketplace/assets/images/default_banner.jpg",
            "vendor_list_banner_type": "image",
            "vendor_list_banner": "http://wclovers.mstore.io/wp-content/plugins/wc-multivendor-marketplace/assets/images/default_banner.jpg",
            "store_rating": 5,
            "email_verified": "",
            "vendor_additional_info": [],
            "vendor_description": "",
            "vendor_policies": {
                "shipping_policy_heading": "Shipping Policy",
                "shipping_policy": "<p><br></p>",
                "refund_policy_heading": "Refund Policy",
                "refund_policy": "<p><br></p>",
                "cancellation_policy_heading": "Cancellation / Return / Exchange Policy",
                "cancellation_policy": "<p><br></p>"
            },
            "store_tab_headings": {
                "products": "Products",
                "about": "About",
                "policies": "Policies",
                "reviews": "Reviews (<span class=\"wcfm_reviews_count\">2</span>)",
                "followers": "Followers (<span class=\"wcfm_followers_count\">1</span>)"
            },
            "settings": null
        },
        "is_purchased": false,
        "attributesData": [
            {
                "id": 1,
                "name": "pa_color",
                "options": [
                    {
                        "term_id": 16,
                        "name": "Black",
                        "slug": "black",
                        "term_group": 0,
                        "term_taxonomy_id": 16,
                        "taxonomy": "pa_color",
                        "description": "",
                        "parent": 0,
                        "count": 4,
                        "filter": "raw"
                    },
                    {
                        "term_id": 18,
                        "name": "Green",
                        "slug": "green",
                        "term_group": 0,
                        "term_taxonomy_id": 18,
                        "taxonomy": "pa_color",
                        "description": "",
                        "parent": 0,
                        "count": 4,
                        "filter": "raw"
                    }
                ],
                "position": 0,
                "visible": false,
                "variation": true,
                "is_visible": 0,
                "is_variation": 1,
                "is_taxonomy": 1,
                "value": "",
                "label": "color"
            }
        ],
        "product_units": {
            "weight_unit": "oz",
            "dimension_unit": "in"
        },
        "wcfm_product_policy_data": {
            "visible": true,
            "shipping_policy": "<p><br></p>",
            "shipping_policy_heading": "Shipping Policy",
            "refund_policy": "<p><br></p>",
            "refund_policy_heading": "Refund Policy",
            "cancellation_policy": "<p><br></p>",
            "cancellation_policy_heading": "Cancellation / Return / Exchange Policy",
            "tab_title": "Store Policies"
        },
        "showAdditionalInfoTab": false,
        "_links": {
            "self": [
                {
                    "href": "https://wclovers.mstore.io/wp-json/wc/v2/products/2198"
                }
            ],
            "collection": [
                {
                    "href": "https://wclovers.mstore.io/wp-json/wc/v2/products"
                }
            ],
            "up": [
                {
                    "href": "https://wclovers.mstore.io/wp-json/wc/v2/products/22"
                }
            ]
        }
    },
    {
        "id": 2196,
        "name": "Apple iPhone 7sssss",
        "slug": "apple-iphone-7s-2",
        "permalink": "https://wclovers.mstore.io/product/apple-iphone-7s-2/",
        "date_created": "2018-08-17T10:40:56",
        "date_created_gmt": "2018-08-17T03:40:56",
        "date_modified": "2021-01-12T02:16:22",
        "date_modified_gmt": "2021-01-11T19:16:22",
        "type": "simple",
        "status": "publish",
        "featured": true,
        "catalog_visibility": "visible",
        "description": "<p>Donec pede justo, fringilla vel, aliquet nec, vulputate eget, arcu. In enim justo, rhoncus ut, imperdiet a, venenatis vitae, justo.zzzzzzzzzz</p>\n",
        "short_description": "<p>Donec pede justo, fringilla vel, aliquet nec, vulputate eget, arcu. In enim justo, rhoncus ut, imperdiet a, venenatis vitae, justo.</p>\n",
        "sku": "12314123",
        "price": "6600",
        "regular_price": "69000",
        "sale_price": "6600",
        "date_on_sale_from": null,
        "date_on_sale_from_gmt": null,
        "date_on_sale_to": null,
        "date_on_sale_to_gmt": null,
        "price_html": "<del><span class=\"woocommerce-Price-amount amount\"><span class=\"woocommerce-Price-currencySymbol\">&#36;</span>69,000.00</span></del> <ins><span class=\"woocommerce-Price-amount amount\"><span class=\"woocommerce-Price-currencySymbol\">&#36;</span>6,600.00</span></ins>",
        "on_sale": true,
        "purchasable": true,
        "total_sales": 12,
        "virtual": false,
        "downloadable": false,
        "downloads": [],
        "download_limit": -1,
        "download_expiry": -1,
        "external_url": "",
        "button_text": "",
        "tax_status": "taxable",
        "tax_class": "",
        "manage_stock": true,
        "stock_quantity": 1106,
        "in_stock": true,
        "backorders": "no",
        "backorders_allowed": false,
        "backordered": false,
        "sold_individually": false,
        "weight": "",
        "dimensions": {
            "length": "",
            "width": "",
            "height": ""
        },
        "shipping_required": true,
        "shipping_taxable": true,
        "shipping_class": "",
        "shipping_class_id": 0,
        "reviews_allowed": true,
        "average_rating": "5.00",
        "rating_count": 1,
        "related_ids": [
            643,
            53,
            1311,
            1644,
            1312
        ],
        "upsell_ids": [],
        "cross_sell_ids": [],
        "parent_id": 1319,
        "purchase_note": "",
        "categories": [
            {
                "id": 64,
                "name": "Accessories",
                "slug": "accessories"
            },
            {
                "id": 32,
                "name": "Camera",
                "slug": "camera"
            },
            {
                "id": 29,
                "name": "Mobile",
                "slug": "mobile"
            }
        ],
        "tags": [
            {
                "id": 88,
                "name": "banner",
                "slug": "banner"
            }
        ],
        "images": [
            {
                "id": 1316,
                "date_created": "2018-05-15T16:35:44",
                "date_created_gmt": "2018-05-15T09:35:44",
                "date_modified": "2018-05-15T16:35:44",
                "date_modified_gmt": "2018-05-15T09:35:44",
                "src": "https://wclovers.mstore.io/wp-content/uploads/2018/05/24.png",
                "name": "24",
                "alt": "",
                "position": 0
            },
            {
                "id": 1315,
                "date_created": "2018-05-15T16:35:42",
                "date_created_gmt": "2018-05-15T09:35:42",
                "date_modified": "2018-05-15T16:35:42",
                "date_modified_gmt": "2018-05-15T09:35:42",
                "src": "https://wclovers.mstore.io/wp-content/uploads/2018/05/23.png",
                "name": "23",
                "alt": "",
                "position": 1
            },
            {
                "id": 1314,
                "date_created": "2018-05-15T16:35:40",
                "date_created_gmt": "2018-05-15T09:35:40",
                "date_modified": "2018-05-15T16:35:40",
                "date_modified_gmt": "2018-05-15T09:35:40",
                "src": "https://wclovers.mstore.io/wp-content/uploads/2018/05/22.png",
                "name": "22",
                "alt": "",
                "position": 2
            }
        ],
        "attributes": [],
        "default_attributes": [],
        "variations": [],
        "grouped_products": [],
        "menu_order": 0,
        "meta_data": [
            {
                "id": 16292,
                "key": "_marketo_deal_date",
                "value": "2019-12-30"
            },
            {
                "id": 16293,
                "key": "_marketo_deal_title",
                "value": "<span class=\"color-primary\">Hurry up!</span> Offers ends in:"
            },
            {
                "id": 16294,
                "key": "pageview",
                "value": "51"
            },
            {
                "id": 16295,
                "key": "_wcmp_child_product",
                "value": "1"
            },
            {
                "id": 16298,
                "key": "slide_template",
                "value": ""
            },
            {
                "id": 16299,
                "key": "_wcmp_cancallation_policy",
                "value": ""
            },
            {
                "id": 16300,
                "key": "_wcmp_refund_policy",
                "value": ""
            },
            {
                "id": 16301,
                "key": "_wcmp_shipping_policy",
                "value": ""
            },
            {
                "id": 16849,
                "key": "_wcfm_product_views",
                "value": "913"
            }
        ],
        "store": {
            "vendor_id": "2",
            "vendor_display_name": null,
            "vendor_shop_name": "Test Ven",
            "formatted_display_name": "Test Ven - Test Ven (#2 - test_vendor)",
            "store_hide_email": "no",
            "store_hide_phone": "no",
            "store_hide_address": "no",
            "store_hide_description": "no",
            "store_hide_policy": "no",
            "store_products_per_page": 10,
            "vendor_email": "vendor@demo.com",
            "disable_vendor": false,
            "is_store_offline": "",
            "vendor_shop_logo": "http://wclovers.mstore.io/wp-content/plugins/wc-frontend-manager/assets/images/wcfmmp-blue.png",
            "vendor_banner_type": "image",
            "vendor_banner": "http://wclovers.mstore.io/wp-content/plugins/wc-multivendor-marketplace/assets/images/default_banner.jpg",
            "mobile_banner": "http://wclovers.mstore.io/wp-content/plugins/wc-multivendor-marketplace/assets/images/default_banner.jpg",
            "vendor_list_banner_type": "image",
            "vendor_list_banner": "http://wclovers.mstore.io/wp-content/plugins/wc-multivendor-marketplace/assets/images/default_banner.jpg",
            "store_rating": 5,
            "email_verified": "",
            "vendor_additional_info": [],
            "vendor_description": "",
            "vendor_policies": {
                "shipping_policy_heading": "Shipping Policy",
                "shipping_policy": "<p><br></p>",
                "refund_policy_heading": "Refund Policy",
                "refund_policy": "<p><br></p>",
                "cancellation_policy_heading": "Cancellation / Return / Exchange Policy",
                "cancellation_policy": "<p><br></p>"
            },
            "store_tab_headings": {
                "products": "Products",
                "about": "About",
                "policies": "Policies",
                "reviews": "Reviews (<span class=\"wcfm_reviews_count\">2</span>)",
                "followers": "Followers (<span class=\"wcfm_followers_count\">1</span>)"
            },
            "settings": null
        },
        "is_purchased": false,
        "attributesData": [],
        "product_units": {
            "weight_unit": "oz",
            "dimension_unit": "in"
        },
        "wcfm_product_policy_data": {
            "visible": true,
            "shipping_policy": "<p><br></p>",
            "shipping_policy_heading": "Shipping Policy",
            "refund_policy": "<p><br></p>",
            "refund_policy_heading": "Refund Policy",
            "cancellation_policy": "<p><br></p>",
            "cancellation_policy_heading": "Cancellation / Return / Exchange Policy",
            "tab_title": "Store Policies"
        },
        "showAdditionalInfoTab": false,
        "_links": {
            "self": [
                {
                    "href": "https://wclovers.mstore.io/wp-json/wc/v2/products/2196"
                }
            ],
            "collection": [
                {
                    "href": "https://wclovers.mstore.io/wp-json/wc/v2/products"
                }
            ],
            "up": [
                {
                    "href": "https://wclovers.mstore.io/wp-json/wc/v2/products/1319"
                }
            ]
        }
    }
]